v3iofs/__init__.py
v3iofs/file.py
v3iofs/fs.py
v3iofs/path.py
v3iofs/utils.py
v3iofs-0.1.18.dist-info/LICENSE.txt
v3iofs-0.1.18.dist-info/METADATA
v3iofs-0.1.18.dist-info/WHEEL
v3iofs-0.1.18.dist-info/top_level.txt
v3iofs-0.1.18.dist-info/RECORD
