Metadata-Version: 2.1
Name: v3iofs
Version: 0.1.18
Summary: fsspec driver for v3io
Home-page: https://github.com/v3io/v3io-fs
Author: Iguazio
Author-email: yaronh@iguazio.com
License: MIT
Classifier: Development Status :: 4 - Beta
Classifier: Intended Audience :: Developers
Classifier: License :: OSI Approved :: Apache Software License
Classifier: Operating System :: POSIX :: Linux
Classifier: Operating System :: Microsoft :: Windows
Classifier: Operating System :: MacOS
Classifier: Programming Language :: Python :: 3
Classifier: Programming Language :: Python :: 3.7
Classifier: Programming Language :: Python :: 3.8
Classifier: Programming Language :: Python :: 3.9
Classifier: Programming Language :: Python
Classifier: Topic :: Software Development :: Libraries :: Python Modules
Classifier: Topic :: Software Development :: Libraries
License-File: LICENSE.txt
Requires-Dist: fsspec >=0.6.2
Requires-Dist: v3io >=0.4.0
